osbot_github/__init__.py
osbot_github/api/GitHub__API.py
osbot_github/api/GitHub__Repo.py
osbot_github/api/__init__.py
osbot_github/api/cache/GitHub__API__Cache.py
osbot_github/api/cache/TestCase__GitHub__API.py
osbot_github/api/cache/__init__.py
osbot_github/dbs/Sqlite__GitHub.py
osbot_github/dbs/Sqlite__GitHub__Files.py
osbot_github/dbs/Sqlite__GitHub__Load_Data.py
osbot_github/dbs/Table__GitHub__Repos.py
osbot_github/dbs/__init__.py
osbot_github/schemas/Schema__Repo.py
osbot_github/schemas/Schema__Repos.py
osbot_github/schemas/__init__.py
osbot_github/utils/Version.py
osbot_github/utils/__init__.py
osbot_github/version
osbot_github-0.5.0.dist-info/LICENSE
osbot_github-0.5.0.dist-info/METADATA
osbot_github-0.5.0.dist-info/WHEEL
osbot_github-0.5.0.dist-info/RECORD
